medilinda_ml/__init__.py
medilinda_ml/columns.py
medilinda_ml/main.py
medilinda_ml/paths.py
medilinda_ml/settings.py
medilinda_ml/utils.py
medilinda_ml/data/clean.py
medilinda_ml/data/load.py
medilinda_ml/data/set_datatypes.py
medilinda_ml/features/build_features.py
medilinda_ml/modeling/train_model.py
medilinda_ml-0.1.7.dist-info/METADATA
medilinda_ml-0.1.7.dist-info/WHEEL
medilinda_ml-0.1.7.dist-info/top_level.txt
medilinda_ml-0.1.7.dist-info/RECORD
