Metadata-Version: 2.4
Name: medilinda-ml
Version: 0.1.7
Summary: Add your description here
Project-URL: Homepage, https://github.com/kraigochieng/medilinda
Classifier: Programming Language :: Python :: 3
Classifier: License :: OSI Approved :: MIT License
Classifier: Operating System :: OS Independent
Classifier: Topic :: Scientific/Engineering :: Artificial Intelligence
Requires-Python: >=3.11
Requires-Dist: build>=1.3.0
Requires-Dist: faker>=37.8.0
Requires-Dist: imbalanced-learn>=0.14.0
Requires-Dist: ipykernel>=6.30.1
Requires-Dist: matplotlib>=3.10.6
Requires-Dist: mlflow>=3.4.0
Requires-Dist: numpy>=2.3.3
Requires-Dist: pandas>=2.3.3
Requires-Dist: pydantic-settings>=2.11.0
Requires-Dist: python-dotenv>=1.1.1
Requires-Dist: scikit-learn>=1.7.2
Requires-Dist: seaborn>=0.13.2
Requires-Dist: shap>=0.48.0
Requires-Dist: twine>=6.2.0
